MANIFEST.in
README.md
requirements.txt
setup.cfg
setup.py
zhihu/__init__.py
zhihu/error.py
zhihu/main.py
zhihu/settings.py
zhihu/url.py
zhihu.egg-info/PKG-INFO
zhihu.egg-info/SOURCES.txt
zhihu.egg-info/dependency_links.txt
zhihu.egg-info/requires.txt
zhihu.egg-info/top_level.txt
zhihu/decorators/__init__.py
zhihu/decorators/auth.py
zhihu/decorators/slug.py
zhihu/models/__init__.py
zhihu/models/account.py
zhihu/models/answer.py
zhihu/models/base.py
zhihu/models/column.py
zhihu/models/message.py
zhihu/models/question.py
zhihu/models/zhihu.py