Metadata-Version: 1.0
Name: zhihu
Version: 0.2.6
Summary: zhihu api from humans
Home-page: https://github.com/lzjun567/zhihu-api
Author: liuzhijun
Author-email: lzjun567@gmail.com
License: MIT License
Platform: UNKNOWN
